discord/ext/cli/__init__.py
discord/ext/cli/channel.py
discord/ext/cli/cli.py
discord/ext/cli/utils.py
discord.ext.cli-3.0.2.dist-info/LICENSE
discord.ext.cli-3.0.2.dist-info/METADATA
discord.ext.cli-3.0.2.dist-info/WHEEL
discord.ext.cli-3.0.2.dist-info/top_level.txt
discord.ext.cli-3.0.2.dist-info/RECORD
