Metadata-Version: 2.1
Name: discord.ext.cli
Version: 3.0.2
Summary: A CLI to talk through console.
Home-page: https://github.com/FrostiiWeeb/discord-ext-cli
Author: Alex Hutz
Author-email: frostiiweeb@gmail.com
License: MIT
Project-URL: Issue Tracker, https://github.com/FrostiiWeeb/discord-ext-cli/issues
Keywords: discord
Platform: UNKNOWN
Classifier: Development Status :: 3 - Alpha
Classifier: Intended Audience :: Developers
Classifier: Topic :: Utilities
Classifier: License :: OSI Approved :: MIT License
Classifier: Programming Language :: Python :: 3.7
Classifier: Programming Language :: Python :: 3.8
Classifier: Programming Language :: Python :: 3.9
Requires-Python: >=3.7.0
License-File: LICENSE
Requires-Dist: aiohttp (>=3.7.3)
Requires-Dist: discord.py (>=1.7.3)
Requires-Dist: waiting
